dyna_store/__init__.py
dyna_store/inmemory.py
dyna_store/main.py
dyna_store-0.0.6.dist-info/METADATA
dyna_store-0.0.6.dist-info/WHEEL
dyna_store-0.0.6.dist-info/RECORD
