Metadata-Version: 2.1
Name: dyna-store
Version: 0.0.6
Summary: Dynamic metadata storage
Home-page: https://github.com/brightnetwork/dyna-store
License: MIT
Keywords: id,meta,store,high-cardinality,metadata
Author: brightnetwork
Author-email: dev@brightnetwork.co.uk
Requires-Python: >=3.10,<4.0
Classifier: License :: OSI Approved :: MIT License
Classifier: Programming Language :: Python :: 3
Classifier: Programming Language :: Python :: 3.10
Classifier: Programming Language :: Python :: 3.11
Classifier: Programming Language :: Python :: 3.12
Requires-Dist: numpy (>=1.0,<3.0)
Project-URL: Documentation, https://github.com/brightnetwork/dyna-store
Project-URL: Repository, https://github.com/brightnetwork/dyna-store
